terrakio_api/__init__.py
terrakio_api_beta-0.4.98.dist-info/METADATA
terrakio_api_beta-0.4.98.dist-info/WHEEL
terrakio_api_beta-0.4.98.dist-info/RECORD
